setup.cfg
setup.py
vaultenv/__init__.py
vaultenv/export.py
vaultenv/main.py
vaultenv/reader.py
vaultenv/settings.py
vaultenv/styles.py
vaultenv.egg-info/PKG-INFO
vaultenv.egg-info/SOURCES.txt
vaultenv.egg-info/dependency_links.txt
vaultenv.egg-info/entry_points.txt
vaultenv.egg-info/not-zip-safe
vaultenv.egg-info/requires.txt
vaultenv.egg-info/top_level.txt