Metadata-Version: 1.0
Name: vaultenv
Version: 0.2.0
Summary: Ansible vault environment variable exporting
Home-page: https://github.com/globality-corp/vaultenv
Author: Globality Engineering
Author-email: engineering@globality.com
License: UNKNOWN
Keywords: vaultenv
Platform: UNKNOWN
